kaara/__init__.py
kaara/__main__.py
kaara/cli/__init__.py
kaara/cli/initial_project/README.md
kaara/cli/run.py
kaara/cli/scaffold.py
kaara/exemple.py
kaara/server.py
kaara/shared/__init__.py
kaara/shared/constants.py
kaara/version.py
kaara-0.1.2.dist-info/METADATA
kaara-0.1.2.dist-info/WHEEL
kaara-0.1.2.dist-info/entry_points.txt
kaara-0.1.2.dist-info/RECORD
