Metadata-Version: 2.1
Name: kaara
Version: 0.1.2
Summary: 
Author: Wingrammer
Author-email: wilpar49@hotmail.com
Requires-Python: >=3.8,<4.0
Classifier: Programming Language :: Python :: 3
Classifier: Programming Language :: Python :: 3.8
Classifier: Programming Language :: Python :: 3.9
Classifier: Programming Language :: Python :: 3.10
Classifier: Programming Language :: Python :: 3.11
Requires-Dist: asgiref (==3.7.2)
Requires-Dist: exceptiongroup (==1.1.3)
Requires-Dist: iniconfig (==2.0.0)
Requires-Dist: packaging (==23.1)
Requires-Dist: pluggy (==1.3.0)
Requires-Dist: prompt-toolkit (==3.0.36)
Requires-Dist: pytest (==7.4.1)
Requires-Dist: questionary (==2.0.0)
Requires-Dist: sqlparse (==0.4.4)
Requires-Dist: tomli (==2.0.1)
Requires-Dist: typing_extensions (==4.7.1)
Requires-Dist: wcwidth (==0.2.6)
